Workbook

Sheet Instructions
A1: Chat British: Practice scenarios (120)
A3: What this is | B3: Practice questions for all 12 categories. Each comes from one approved taxonomy entry. The app uses only rows whose Status is Approved.
A4: How they were made | B4: AI-drafted (Claude) from your approved taxonomy entries. The setup comes from the entry's example and surface markers, the right answer from its Good Response, the wrong answers from the misreadings the entry warns about, and the feedback restates its "What It Actually Means". Legal and statistical details in the entries were left out of the feedback on purpose.
A5: Approval record | B5: All rows are Approved because the founder accepted the whole set. The Review state column records what that means: 24 rows (the original 6 and batch 1) were read and approved individually; the other 96 were accepted in bulk and still need an item-by-item read. Please change Review state to "Reviewed and approved by founder" as you go. Do not remove the column.
A6: Spot-check first | B6: Fifteen of the bulk-approved rows are marked yellow in the Spot-check first column, at least one per category. Reading those first (about 10 minutes) tells you whether the rest need changes.
A7: What to edit | B7: Any text in the blue cells. Set Status to Needs edit or Rejected for anything that shouldn't be shown (it then disappears from the app on the next import). Use Review notes for changes you want but haven't made.
A8: Length | B8: The Longest feedback column turns red above 180 characters. Longer feedback makes the answer panel tall on a phone.
A9: Colour key | B9: Light blue = AI-drafted. Yellow = spot-check first. Grey = reference text from the taxonomy; do not edit.
A10: Columns | B10: Scenario ID is unique and never reused. Norm ID is the taxonomy entry it comes from. The right answer appears in a random position in the app.
A12: Category | B12: In this file | C12: Already in the app | D12: Total | E12: Source of the app figure
A13: Workplace | B13: =COUNTIF(Scenarios!$C$2:$C$601,A13) | C13: 0 | D13: =B13+C13 | E13: All scenarios now live in this workbook.
A14: Healthcare | B14: =COUNTIF(Scenarios!$C$2:$C$601,A14) | C14: 0 | D14: =B14+C14
A15: Housing & landlord | B15: =COUNTIF(Scenarios!$C$2:$C$601,A15) | C15: 0 | D15: =B15+C15
A16: Job search | B16: =COUNTIF(Scenarios!$C$2:$C$601,A16) | C16: 0 | D16: =B16+C16
A17: Social | B17: =COUNTIF(Scenarios!$C$2:$C$601,A17) | C17: 0 | D17: =B17+C17
A18: Admin & bureaucracy | B18: =COUNTIF(Scenarios!$C$2:$C$601,A18) | C18: 0 | D18: =B18+C18
A19: Education | B19: =COUNTIF(Scenarios!$C$2:$C$601,A19) | C19: 0 | D19: =B19+C19
A20: Dating & relationships | B20: =COUNTIF(Scenarios!$C$2:$C$601,A20) | C20: 0 | D20: =B20+C20
A21: Money & transactions | B21: =COUNTIF(Scenarios!$C$2:$C$601,A21) | C21: 0 | D21: =B21+C21
A22: Transport & commuting | B22: =COUNTIF(Scenarios!$C$2:$C$601,A22) | C22: 0 | D22: =B22+C22
A23: Neighbours & community | B23: =COUNTIF(Scenarios!$C$2:$C$601,A23) | C23: 0 | D23: =B23+C23
A24: Customer service & retail | B24: =COUNTIF(Scenarios!$C$2:$C$601,A24) | C24: 0 | D24: =B24+C24
A25: Total | B25: =SUM(B13:B24) | C25: =SUM(C13:C24) | D25: =SUM(D13:D24)

Sheet Scenarios
A1: Scenario ID | B1: Norm ID | C1: Category | D1: Setup | E1: Prompt | F1: Right answer | G1: Right-answer feedback | H1: Wrong answer 1 | I1: Wrong 1 feedback | J1: Wrong answer 2 | K1: Wrong 2 feedback | L1: Status | M1: Review state | N1: Spot-check first | O1: Review notes | P1: Longest feedback (chars) | Q1: Entry: What It Actually Means | R1: Entry: Good Response
A2: SC-WP-2-a | B2: WP-2-promotion-discussion-indirectness | C2: Workplace | D2: You ask your manager about a promotion. She says, “It's definitely something we can look at.” No date is mentioned. | E2: What do you do? | F2: Ask to set a date to revisit it, and what she'd want to see from you before then. | G2: Warm language isn't a promise. A real commitment usually comes with a date or a documented next step. | H2: Take it as a near-term commitment and wait. | I2: It's a deferral, not a promise. With no date attached, nothing is actually in motion. | J2: Drop the subject so you don't seem pushy. | K2: Asking for a concrete next step is normal. Dropping it leaves a vague deferral vague. | L2: Approved | M2: Bulk-approved by founder; item review pending | P2: =MAX(LEN(G2),LEN(I2),LEN(K2)) | Q2: Not a promise — it's a deferral. A real commitment usually comes with a specific date or documented next step, not just warm language. | R2: Ask for something concrete: "Could we set a specific date to revisit this, and what would you want to see from me before then?"
A3: SC-WP-4-a | B3: WP-4-deadline-reminder-escalation | C3: Workplace | D3: Your manager emails: “Just a gentle reminder about the report.” Three days later: “Following up again on this.” You haven't sent it yet. | E3: How do you read the second email? | F3: As rising urgency. Treat the task as a priority now. | G3: Repetition is the real signal. Each “gentle” reminder means urgency is rising, however mild it sounds. | H3: As routine politeness. There's still no rush. | I3: The wording stays polite, but a second follow-up on the same task is a priority signal. | J3: Wait for a third reminder before acting. | K3: The third is usually direct, such as “I need this by end of day”. Don't wait for it. | L3: Approved | M3: Bulk-approved by founder; item review pending | N3: Yes | P3: =MAX(LEN(G3),LEN(I3),LEN(K3)) | Q3: Each repeated "gentle" reminder signals rising urgency, even though the wording stays polite — treat repetition itself as the real signal. | R3: Treat any second follow-up on the same task as a priority signal, regardless of how mild the wording still sounds.
A4: SC-WP-6-a | B4: WP-6-agreement-in-meetings-silence | C4: Workplace | D4: You present a plan in a team meeting. Everyone nods and says it could work. Nobody pushes back. | E4: What do you do next? | F4: Check with key people one by one: “Any concerns before I move ahead?” | G4: Real objections are often saved for a private conversation, so agreement in the room can be provisional. | H4: Treat it as settled and go ahead. | I4: Agreement in the room can be provisional. Concerns often arrive later, in private. | J4: Ask the whole group again if anyone disagrees. | K4: People rarely voice objections in front of the group. A private follow-up invites them. | L4: Approved | M4: Bulk-approved by founder; item review pending | P4: =MAX(LEN(G4),LEN(I4),LEN(K4)) | Q4: Real objections are often saved for a private, one-on-one follow-up rather than voiced in front of the group — the meeting-room agreement can be provisional, not final. | R4: After a meeting where a decision was made, follow up individually with key people: “Any concerns before I move ahead with this?” — invites private pushback before it's too late to change course.
A5: SC-WP-7-a | B5: WP-7-cc-escalation-email | C5: Workplace | D5: In a routine email chain about a project, a colleague suddenly CCs your manager. There's no explanation and the tone stays friendly. | E5: What does the CC most likely mean? | F5: The issue is being put on record. Ask plainly if there's a concern to address. | G5: A sudden CC often marks the point an issue is formally tracked, even when the tone stays friendly. | H5: Nothing. It's just keeping people in the loop. | I5: With no explanation, a new CC usually means the sender wants it on record. | J5: A friendly gesture to share credit. | K5: The friendly tone can mislead. A new CC with no explanation more often signals escalation. | L5: Approved | M5: Bulk-approved by founder; item review pending | P5: =MAX(LEN(G5),LEN(I5),LEN(K5)) | Q5: This often marks the point an issue is being formally tracked or escalated, even though the email's tone may stay friendly and unchanged. | R5: When newly CC'd people appear, ask plainly: “Just flagging — is there a concern here I should be addressing directly?”
A6: SC-WP-8-a | B6: WP-8-sorry-to-bother-request | C6: Workplace | D6: Your manager says: “Sorry to bother you, this is probably nothing, but could you rewrite the report by end of day?” | E6: How big is the ask? | F6: As big as it sounds: a full rewrite, due today. | G6: The apology softens the tone, not the size or urgency. Take the request itself at face value. | H6: Small. They said it's probably nothing. | I6: The “probably nothing” is politeness. A same-day rewrite is a substantial request. | J6: Fine to do later in the week. | K6: The deadline in the request is real, whatever the soft opening says. | L6: Approved | M6: Bulk-approved by founder; item review pending | P6: =MAX(LEN(G6),LEN(I6),LEN(K6)) | Q6: The apology softens the tone of the request but doesn't reflect its actual size or urgency — take the request itself at face value, not the apology. | R6: Treat the substance of the ask, not the softening language, as the real signal of urgency and size.
A7: SC-WP-10-a | B7: WP-10-feedback-sandwich | C7: Workplace | D7: Your manager says: “Great presentation. Maybe tighten the data section next time, but overall really well done.” | E7: What's the main thing to take from this? | F7: The data section needs work. Repeat it back to confirm. | G7: The critical point often sits in the middle: short in words, but not small in importance. | H7: That it went really well and nothing needs changing. | I7: That misses the middle comment, which is often the real point of the feedback. | J7: That your manager thought the whole presentation was weak. | K7: That's an overreaction. The specific point is the data section, not the whole presentation. | L7: Approved | M7: Bulk-approved by founder; item review pending | P7: =MAX(LEN(G7),LEN(I7),LEN(K7)) | Q7: The middle comment is often the actual, most important point of the feedback — proportionally small wording doesn't mean proportionally small importance. | R7: When feedback includes a “middle” point, repeat it back to confirm: “So the main thing to work on is the data section — got it.”
A8: SC-WP-12-a | B8: WP-12-calendar-invite-formality | C8: Workplace | D8: After weeks of casual chat messages, your manager sends a calendar invite with a specific title and agenda for the same topic. | E8: How do you approach the meeting? | F8: Prepare as for a formal conversation. | G8: Moving from chat to a scheduled invite is itself a signal the matter is being taken more seriously. | H8: Treat it as routine and go in unprepared. | I8: An invite for a topic normally handled informally is a shift. Assuming it's routine misses it. | J8: Ask to keep it as an informal chat instead. | K8: The formal invite was a deliberate choice. Preparing for it is the safer reading. | L8: Approved | M8: Bulk-approved by founder; item review pending | P8: =MAX(LEN(G8),LEN(I8),LEN(K8)) | Q8: The shift from informal chat to a scheduled invite is itself a signal the matter is being taken more seriously or formally than before. | R8: When an invite appears for a topic normally handled informally, prepare as if for a formal conversation rather than assuming it's purely routine.
A9: SC-WP-13-a | B9: WP-13-not-the-right-forum | C9: Workplace | D9: In a team meeting you raise a budget concern. The lead replies, “This might not be the right forum for that.” | E9: What do you do? | F9: Follow up directly afterwards: “Could we find 15 minutes to go through the budget point?” | G9: It usually means they don't want to address it in front of the group, not that the point is wrong. | H9: Wait for them to bring it up again. | I9: Without a follow-up from you, it usually never comes back. | J9: Assume the budget concern doesn't matter. | K9: It's the venue they're avoiding, not the issue. A direct follow-up gets it heard. | L9: Approved | M9: Bulk-approved by founder; item review pending | P9: =MAX(LEN(G9),LEN(I9),LEN(K9)) | Q9: This usually means the person doesn't want to address the point in front of the group, not that the venue is genuinely wrong. | R9: Follow up directly and specifically afterward: "Could we find 15 minutes to go through the budget point from earlier?" rather than waiting for the other person to raise it again.
A10: SC-WP-15-a | B10: WP-15-meeting-jargon-deferral | C10: Workplace | D10: A colleague loves your idea in a meeting. The lead says, “Let's park that for now.” No date or owner is mentioned. | E10: What do you do? | F10: Ask for a next step on the spot: “Who should bring this back, and roughly when?” | G10: Without a concrete next step, a parked topic often quietly drops. | H10: Assume it will be revisited soon. | I10: It usually isn't, unless someone owns it and a date is set. | J10: Take it as a polite no and forget it. | K10: It may not be a no. Asking for an owner and a date finds out. | L10: Approved | M10: Bulk-approved by founder; item review pending | P10: =MAX(LEN(G10),LEN(I10),LEN(K10)) | Q10: Without a concrete next step attached, "parking" a topic often means it quietly drops rather than genuinely pausing. | R10: When something is parked, ask for a concrete next step on the spot: "Who should own bringing this back, and roughly when?"
A11: SC-HC-2-a | B11: HC-2-referral-wait-silence | C11: Healthcare | D11: Six weeks after a GP referral you've heard nothing. The letter said, “We'll be in touch once it's been reviewed.” | E11: What do you do? | F11: Call the surgery or referral line to check the status. | G11: Long waits reflect NHS process and backlog, not a dropped case. Asking is normal and expected. | H11: Assume the request was lost, and give up. | I11: Silence is common and doesn't mean your case was dropped. Checking is how you find out. | J11: Wait quietly, since calling would be rude. | K11: It isn't rude. Calling to check status is normal and expected. | L11: Approved | M11: Bulk-approved by founder; item review pending | P11: =MAX(LEN(G11),LEN(I11),LEN(K11)) | Q11: This reflects NHS process/backlog, not that the case was dropped — the official standard is 18 weeks from referral to treatment, but as of 2026 only around two-thirds of patients are actually being seen within that window nationally, so a longer wait is common, not exceptional. | R11: Call the GP surgery or hospital referral line directly to check status rather than assuming; this is normal and expected, not rude to ask.
A12: SC-HC-3-a | B12: HC-3-nhs-111-triage-language | C12: Healthcare | D12: You phone 111 about a minor problem. The call ends with a long list: “If you get any of these symptoms, go to A&E immediately.” | E12: How do you read the list? | F12: As standard safety wording. Ask how urgent your case is specifically. | G12: It's standard safety wording given to nearly everyone, not a specific escalation of your case. | H12: As a sign your case is more serious than they said. | I12: That's the common panic. The list is given to almost everyone. | J12: As something to ignore completely. | K12: Better to ask: “How urgent is this specifically?” That tells you what it means for you. | L12: Approved | M12: Bulk-approved by founder; item review pending | P12: =MAX(LEN(G12),LEN(I12),LEN(K12)) | Q12: This is defensive, standardized safety language given to nearly everyone, not a specific escalation of concern about your individual case. | R12: Ask directly: “Based on what I've told you, how urgent is this specifically?” rather than reading the standard safety list as a signal.
A13: SC-HC-4-a | B13: HC-4-pharmacist-first-point-of-contact | C13: Healthcare | D13: You ring the surgery about a sore throat. The receptionist says, “Try the pharmacy first.” | E13: What does that mean? | F13: A standard route for minor issues. If symptoms persist, ask for a GP appointment. | G13: For minor issues it's an expected referral, not the surgery deflecting or downgrading your concern. | H13: That the surgery is brushing you off. | I13: It's a standard route for minor conditions, not a dismissal. | J13: That you should never see a GP for this. | K13: Not never. If symptoms persist after the pharmacy, that's the natural point to ask for a GP. | L13: Approved | M13: Bulk-approved by founder; item review pending | P13: =MAX(LEN(G13),LEN(I13),LEN(K13)) | Q13: This is a standard, expected referral for minor issues (rashes, coughs, UTIs, etc.), not the surgery deflecting or downgrading the concern. | R13: Treat a pharmacist referral as a genuine, appropriate option — and if symptoms persist after, that's the natural point to request a GP appointment.
A14: SC-HC-5-a | B14: HC-5-patient-advocating-for-self | C14: Healthcare | D14: Your GP appointment is nearly over. The doctor says briefly, “Anything else?” You have a second, worrying symptom you haven't mentioned. | E14: What do you do? | F14: Say it directly: “Yes, there's one more thing I want to cover.” | G14: The system expects you to raise what matters. Staying quiet out of politeness reads as “nothing else”. | H14: Say “No, that's all” so you don't take up their time. | I14: That's read as nothing else, and the appointment ends without your main concern. | J14: Hint at it and hope the doctor picks up on it. | K14: A hint usually isn't picked up. State what matters directly and early. | L14: Approved | M14: Bulk-approved by founder; item review pending | P14: =MAX(LEN(G14),LEN(I14),LEN(K14)) | Q14: The system expects the patient to raise what matters to them proactively; staying quiet out of politeness or deference is read as “nothing else,” not as holding back out of respect. | R14: Prepare your 1-2 main points beforehand and state them directly and early: “There are two things I want to cover today: X and Y.”
A15: SC-HC-8-a | B15: HC-8-watchful-waiting-approach | C15: Healthcare | D15: For a minor symptom the GP says, “Let's give it two weeks and see how it settles.” No tests or referral are offered. | E15: What do you do? | F15: Ask what signs would mean coming back sooner than two weeks. | G15: It's a deliberate strategy for conditions that often settle on their own, not a sign your concern is unimportant. | H15: Conclude the GP isn't taking you seriously. | I15: Waiting and reviewing is standard practice for many minor conditions. | J15: Don't go back at all unless it gets much worse. | K15: The plan depends on you returning if it hasn't improved, so ask what to watch for. | L15: Approved | M15: Bulk-approved by founder; item review pending | P15: =MAX(LEN(G15),LEN(I15),LEN(K15)) | Q15: This is a deliberate, evidence-based strategy for self-limiting conditions, not a sign the GP thinks the concern is unimportant. | R15: Ask directly what to watch for and when to return: "What specific signs would mean I should come back sooner than two weeks?"
A16: SC-HC-9-a | B16: HC-9-econsult-online-triage-form | C16: Healthcare | D16: You ring your surgery and are told, “Please fill in the online form instead.” | E16: How do you take it? | F16: As the standard route. Use the form, and be specific and complete. | G16: It's the surgery's standard way of managing demand, not a barrier set against your request. | H16: As a brush-off. Keep ringing until someone answers. | I16: The form is how requests are normally triaged, often faster than expected. | J16: Fill it in with just a few words to save time. | K16: Be specific and complete. A detailed form is easier to triage properly. | L16: Approved | M16: Bulk-approved by founder; item review pending | N16: Yes | P16: =MAX(LEN(G16),LEN(I16),LEN(K16)) | Q16: This is the surgery's standard triage process for managing demand, not a barrier placed specifically in front of this particular request. | R16: Use the online form as the primary channel and be specific and complete in it, since it's often triaged faster than expected.
A17: SC-HC-10-a | B17: HC-10-same-day-urgent-only-gatekeeping | C17: Healthcare | D17: You call for an appointment and the receptionist asks, “Can I ask what it's regarding, so I can see who's best to help?” You feel embarrassed. | E17: What do you do? | F17: Answer factually and specifically, including how long you've had it. | G17: It's a standard triage question asked of everyone, not a test of whether your concern is valid. | H17: Refuse to say, since it's private. | I17: The question is routine. Answering helps route you to the right type of appointment. | J17: Stay vague so you don't seem to be fussing. | K17: Specifics get you routed faster. A vague answer makes the right appointment harder to pick. | L17: Approved | M17: Bulk-approved by founder; item review pending | P17: =MAX(LEN(G17),LEN(I17),LEN(K17)) | Q17: This question is a standard triage step for every patient, not scrutiny of whether this specific concern is valid. | R17: Answer the triage question factually and specifically, including how long the issue has lasted, to get routed to the right appointment type faster.
A18: SC-HC-11-a | B18: HC-11-ae-triage-wait-times | C18: Healthcare | D18: At A&E a nurse sees you briefly, then you wait in the main waiting area for hours with no update. | E18: What does the long wait most likely mean? | F18: You've been assessed as less urgent than others. It's fine to ask for a rough update. | G18: A long wait after triage usually means lower urgency compared with others, not that you were overlooked. | H18: That you've been forgotten. | I18: You've been assessed. Asking the desk for a rough update is acceptable. | J18: That something is seriously wrong and nobody is telling you. | K18: The opposite is more likely. More urgent cases are seen first. | L18: Approved | M18: Bulk-approved by founder; item review pending | P18: =MAX(LEN(G18),LEN(I18),LEN(K18)) | Q18: A long wait after initial triage typically confirms the case has been assessed as lower urgency relative to others being treated, not that it was overlooked. | R18: It's acceptable to ask the desk for a rough update after a long wait: "Just checking I'm still in the queue — any sense of how much longer?"
A19: SC-HC-15-a | B19: HC-15-second-opinion-request-phrasing | C19: Healthcare | D19: You want a second opinion on a diagnosis, but it feels rude to say so to your GP. | E19: What do you say? | F19: “I'd like a second opinion. Could you point me toward how to arrange that?” | G19: A plain request is acceptable. Softening is a politeness habit, not a sign you shouldn't ask. | H19: “Is there anyone else I could possibly speak to?” and leave it there. | I19: The hedged version can go unnoticed. Say plainly that you want a second opinion. | J19: Wait a few weeks, then try again. | K19: Delay doesn't help. It's a normal, accepted request, so make it plainly now. | L19: Approved | M19: Bulk-approved by founder; item review pending | P19: =MAX(LEN(G19),LEN(I19),LEN(K19)) | Q19: This is a normal, accepted request even when phrased softly — the hedging is a politeness convention, not a sign the patient shouldn't ask. | R19: It's acceptable to state the request plainly: "I'd like to get a second opinion on this — could you point me toward how to arrange that?"
A20: SC-HL-2-a | B20: HL-2-passive-aggressive-written-notice | C20: Housing & landlord | D20: Your neighbour leaves a note: “Just a friendly reminder about bin day, hope you don't mind me asking.” It's the third note. | E20: How do you read it? | F20: As a firm complaint. Respond to the practical issue directly. | G20: The politeness is a buffer. The underlying message is a firm complaint, not a casual suggestion. | H20: As a casual suggestion you can leave for now. | I20: A repeated “friendly” note means the issue isn't casual. | J20: As a joke between neighbours. | K20: Nothing playful. The soft wording hides a real complaint, so deal with the practical issue. | L20: Approved | M20: Bulk-approved by founder; item review pending | P20: =MAX(LEN(G20),LEN(I20),LEN(K20)) | Q20: The politeness is a social buffer — the underlying message is a firm complaint, not a casual suggestion. | R20: Treat the specific ask as the real message regardless of the soft wording, and respond to the practical issue directly.
A21: SC-HL-3-a | B21: HL-3-inventory-check-in-formality | C21: Housing & landlord | D21: When you move in, the landlord hands you a long inventory listing every mark and scuff, and seems keen to have it signed quickly. | E21: What do you do? | F21: Check it thoroughly, and add notes and photos for anything inaccurate before signing. | G21: The inventory is your main protection against unfair deposit deductions later. | H21: Sign quickly to seem agreeable. | I21: Rushing is how people end up unable to dispute a deduction for a mark that was already there. | J21: Skip it, since a long list is excessive. | K21: It isn't excessive. Skipping a careful read works against your own interest. | L21: Approved | M21: Bulk-approved by founder; item review pending | P21: =MAX(LEN(G21),LEN(I21),LEN(K21)) | Q21: This document is the tenant's main protection against unfair deposit deductions later — treating it as excessive or skipping a careful read works against the tenant's own interest. | R21: Take time to check the inventory thoroughly and add notes/photos for anything inaccurate before signing, regardless of how quick the landlord seems to want it done.
A22: SC-HL-6-a | B22: HL-6-shared-house-kitchen-etiquette-notes | C22: Housing & landlord | D22: A note appears on the fridge: “Can everyone please remember to wash up their own dishes :)” You've left a few plates. | E22: How do you read the note? | F22: As the end of a build-up. Respond promptly, in person if you can. | G22: By the time a note appears, the issue has usually been building for a while. | H22: As a light, general reminder. | I22: The smiley is friendly, but it's rarely the first time it has bothered someone. | J22: As aimed at someone else, so ignore it. | K22: Notes like this rarely come from nowhere. A prompt, direct response beats hoping it's about someone else. | L22: Approved | M22: Bulk-approved by founder; item review pending | P22: =MAX(LEN(G22),LEN(I22),LEN(K22)) | Q22: By the time a note appears, the issue has likely been building for a while — it's rarely the first time it's bothered someone. | R22: Respond to a shared-space note promptly and directly, and consider a brief in-person acknowledgment: “Sorry, I'll sort that — let me know if it's been an ongoing issue.”
A23: SC-HL-7-a | B23: HL-7-viewing-feedback-silence | C23: Housing & landlord | D23: After a flat viewing the agent says, “We'll let you know.” Two weeks pass with no contact. | E23: What do you do? | F23: Treat it as a likely no, keep viewing other flats, and follow up once politely. | G23: Silence past the expected time functions as the rejection. An explicit “no” is uncommon. | H23: Keep waiting. They said they'd let you know. | I23: That's how people miss other options. Silence past the timeframe is usually the answer. | J23: Phone every day until you get a clear answer. | K23: One polite follow-up is enough. Meanwhile keep looking at other properties. | L23: Approved | M23: Bulk-approved by founder; item review pending | P23: =MAX(LEN(G23),LEN(I23),LEN(K23)) | Q23: Silence past the expected timeframe functions as the rejection in UK rental practice — an explicit “no” is uncommon. | R23: Treat silence past the stated timeframe as a likely no and keep actively viewing other properties in parallel, following up once politely for a final answer.
A24: SC-HL-8-a | B24: HL-8-referencing-in-progress-delay | C24: Housing & landlord | D24: You've applied for a flat. For over a week the agent keeps saying, “Referencing is still being processed, we'll update you as soon as we hear.” | E24: What do you do? | F24: Ask which reference is outstanding, and offer to help chase it. | G24: Referencing depends on outside providers replying, which is often the real bottleneck. | H24: Assume you've been rejected. | I24: A slow previous landlord or employer can hold things up without any rejection. | J24: Keep waiting without asking. | K24: A specific question gets further: which reference is outstanding, and can you help? | L24: Approved | M24: Bulk-approved by founder; item review pending | P24: =MAX(LEN(G24),LEN(I24),LEN(K24)) | Q24: Referencing depends on external providers (employers, previous landlords, credit agencies) responding, which is often the actual bottleneck, not agent inaction. | R24: Ask specifically which part of referencing is outstanding: "Is there a particular reference we're still waiting on that I could help chase?"
A25: SC-HL-12-a | B25: HL-12-income-affordability-multiplier | C25: Housing & landlord | D25: A letting agent says your income must be at least a set multiple of the rent. Yours is just below, but you have strong savings. | E25: What do you do? | F25: Ask whether savings or a larger upfront payment could be offered instead. | G25: The multiplier is a standard formula, not a judgement of you. Alternatives are worth asking about. | H25: Take it as a rejection and stop pursuing this flat. | I25: It's a uniform formula, not a verdict on you. Asking about alternatives costs nothing. | J25: Argue that the rule is unfair. | K25: The formula is applied to everyone. Offering a concrete alternative is the better route. | L25: Approved | M25: Bulk-approved by founder; item review pending | P25: =MAX(LEN(G25),LEN(I25),LEN(K25)) | Q25: This is a standardized formula applied uniformly, not a judgment about this specific applicant's overall financial reliability — and since the Renters' Rights Act 2025, it's now unlawful for a landlord or agent to refuse an otherwise-qualifying applicant, or make renting harder for them, because they receive benefits or have children (councils can fine up to £7,000 for breaching this). | R25: If income is close to the threshold, ask directly whether savings or a larger upfront payment can be offered as an alternative to meeting the multiplier exactly.
A26: SC-HL-14-a | B26: HL-14-permitted-occupiers-clause | C26: Housing & landlord | D26: Your partner has been staying with you for a few months. The tenancy lists named occupiers only. The landlord seemed relaxed when you mentioned it casually. | E26: What do you do? | F26: Ask for a written update to the agreement. | G26: A relaxed landlord doesn't override the written clause. A long-term guest needs formal agreement. | H26: Rely on the landlord's friendly reaction. | I26: A casual OK isn't a written change, and a long stay can still breach the clause. | J26: Say nothing, since nobody has complained. | K26: Silence leaves the clause breached. Beyond a couple of weeks, ask for it in writing. | L26: Approved | M26: Bulk-approved by founder; item review pending | P26: =MAX(LEN(G26),LEN(I26),LEN(K26)) | Q26: A landlord being personally relaxed in conversation doesn't override the written clause — a guest staying long-term can still be a genuine breach if not addressed formally. | R26: For any guest staying beyond a couple of weeks, request a written update to the agreement rather than relying on a verbal heads-up.
A27: SC-HL-15-a | B27: HL-15-break-clause-deferral | C27: Housing & landlord | D27: You ask your landlord to let you leave a few months early. He says, “Let me check with the agency and get back to you.” Nothing follows. | E27: What do you do? | F27: Ask for an answer by a specific date, since you need to plan. | G27: It may be a genuine step, but it can also buy time. A deadline moves things forward. | H27: Wait for them to come back to you. | I27: Waiting leaves it open-ended. A date makes a reply, or a refusal, harder to avoid. | J27: Take the silence as permission to leave. | K27: Silence isn't agreement. Ask for a clear answer by a date you name. | L27: Approved | M27: Bulk-approved by founder; item review pending | P27: =MAX(LEN(G27),LEN(I27),LEN(K27)) | Q27: This may be a genuine process step, but it can also be a way of buying time or softening a refusal. Since May 2026, most tenancies are periodic from the start, and a tenant can generally end one by giving at least two months' written notice, without needing a landlord's agreement at all. | R27: Set a specific follow-up date when asking: "Could you let me know by [date] either way, since I need to plan my next steps?"
A28: SC-HL-16-a | B28: HL-16-end-of-tenancy-cleaning-checklist | C28: Housing & landlord | D28: Before moving out you clean the whole flat thoroughly yourself. The inventory mentions a “professional clean” standard. | E28: What do you do? | F28: Check the exact cleaning clause, and book a professional clean with a receipt if it asks for one. | G28: Your own cleaning may not meet the contract's standard, however clean the flat looks. | H28: Rely on your own deep clean. | I28: Without the professional service and receipt, the cleaning standard may still not be met. | J28: Ask the landlord to judge it by eye. | K28: The contract sets the standard, not how the flat looks. Check the exact clause first. | L28: Approved | M28: Bulk-approved by founder; item review pending | N28: Yes | P28: =MAX(LEN(G28),LEN(I28),LEN(K28)) | Q28: A tenant's own thorough cleaning may not meet the specific contractual standard unless a professional service and receipt are provided, regardless of how clean the property looks. | R28: Check the tenancy agreement's exact cleaning clause before moving out, and book a professional clean with a receipt if that's what's specified.
A29: SC-JS-2-a | B29: JS-2-salary-negotiation-indirectness | C29: Job search | D29: In a first interview they ask, “What's your expected salary range?” before mentioning any number. | E29: What do you do? | F29: Give a confident, well-researched range. | G29: It's a negotiation norm. Stating a researched range is expected, not pushy. | H29: Say “I'm flexible, whatever you think is fair.” | I29: A vague answer leaves you without a position and can read as unprepared. | J29: Say you'd rather not talk about money yet. | K29: It's a routine question here. Deflecting it reads as unprepared. | L29: Approved | M29: Bulk-approved by founder; item review pending | P29: =MAX(LEN(G29),LEN(I29),LEN(K29)) | Q29: This is a negotiation norm, not evasiveness — giving a well-researched range in response is expected and normal, not pushy. | R29: Research the market range beforehand and state a confident range when asked, rather than deflecting the question.
A30: SC-JS-3-a | B30: JS-3-cv-personal-statement-understatement | C30: Job search | D30: Your CV is full of words like “exceptional” and “outstanding”. UK recruiters give polite but cool feedback. | E30: What do you change? | F30: Lead with specific, factual results: numbers and concrete outcomes. | G30: Understated, evidence-led writing reads as credible. Heavy self-promotion can read as less so. | H30: Make the claims even stronger to stand out. | I30: In some UK sectors, extreme self-promotion can read as less credible. | J30: Remove your achievements to look modest. | K30: Modesty doesn't mean hiding results. Let the numbers carry the weight, not the adjectives. | L30: Approved | M30: Bulk-approved by founder; item review pending | P30: =MAX(LEN(G30),LEN(I30),LEN(K30)) | Q30: Understated language is not a lack of confidence in this context — being extremely self-promotional can actually read as less credible in some UK sectors, particularly traditional or public-sector ones. | R30: Lead with specific, factual outcomes (numbers, concrete results) rather than superlative language — let the evidence carry the weight instead of the adjectives.
A31: SC-JS-4-a | B31: JS-4-recruiter-warm-language-non-commitment | C31: Job search | D31: A recruiter tells you, “You're a really strong candidate, the client loved you.” No next step or date is mentioned. | E31: How do you read it? | F31: As friendly encouragement. Ask for the next formal step and when you'll hear. | G31: It's standard relationship-management language, not a reliable signal of where you stand. | H31: As a near-certain offer. | I31: Warmth isn't commitment. Many candidates hear this and don't get an offer. | J31: As a lie to ignore. | K31: It isn't a lie, just routine warmth. Ask what the next formal step is and by when. | L31: Approved | M31: Bulk-approved by founder; item review pending | P31: =MAX(LEN(G31),LEN(I31),LEN(K31)) | Q31: This is standard relationship-management language recruiters use with most candidates to keep them engaged, not a reliable signal of where you stand. | R31: Ask directly for concrete next steps and timelines rather than reading warmth as commitment: “What's the next formal step, and by when should I expect to hear?”
A32: SC-JS-5-a | B32: JS-5-competency-question-structure-expectation | C32: Job search | D32: In an interview you're asked, “Tell me about a time you had to deal with a difficult colleague.” The interviewer waits. | E32: How do you answer? | F32: Give a specific example: the situation, your task, what you did and the result. | G32: A structured, specific past example is what's being assessed. | H32: Explain your general approach: “I always try to communicate well.” | I32: A general philosophy reads as unprepared. | J32: Say you've never had a difficult colleague. | K32: That doesn't answer the question. Prepare real examples in advance. | L32: Approved | M32: Bulk-approved by founder; item review pending | P32: =MAX(LEN(G32),LEN(I32),LEN(K32)) | Q32: A vague or general answer (“I always try to communicate well”) reads as unprepared — a specific, structured past example is what's actually being assessed. | R32: Prepare 4-5 specific past examples in advance, structured as situation → task → action → result, ready to adapt to different competency questions.
A33: SC-JS-6-a | B33: JS-6-notice-period-negotiation-norm | C33: Job search | D33: In an interview they ask, “When could you start?” You have a month's notice at your current job. | E33: What do you say? | F33: State your real notice period, and add that you're keen to start as soon as it allows. | G33: Employers plan around standard notice periods. Honesty here is the norm, not a risk. | H33: Say you can start immediately, to seem keen. | I33: A shorter-than-normal answer isn't needed to show keenness. | J33: Avoid answering until you have an offer. | K33: It's a routine question. A plain answer with some enthusiasm works better. | L33: Approved | M33: Bulk-approved by founder; item review pending | P33: =MAX(LEN(G33),LEN(I33),LEN(K33)) | Q33: Employers expect and plan around a standard notice period; a shorter-than-normal answer isn't required to demonstrate keenness, and honesty here is the norm, not a risk. | R33: State the real notice period plainly and, if genuinely relevant, add a brief note of enthusiasm: “My notice period is one month, but I'm very keen to start as soon as that allows.”
A34: SC-JS-7-a | B34: JS-7-networking-coffee-informality | C34: Job search | D34: A senior contact in your field says, “Would you fancy a coffee sometime to chat about the sector?” | E34: How do you treat it? | F34: As a real opportunity. Prepare a few relevant points or questions. | G34: It's a standard, taken-seriously way to build a professional relationship. | H34: As purely social, so go without preparing. | I34: It's informal in tone but not in purpose. Prepare as you would for a formal meeting. | J34: As vague politeness that probably won't happen. | K34: It's a genuine invitation. Treat it as a real conversation. | L34: Approved | M34: Bulk-approved by founder; item review pending | P34: =MAX(LEN(G34),LEN(I34),LEN(K34)) | Q34: This is a standard, taken-seriously way to build a professional relationship or explore an opportunity informally — showing up prepared and treating it as a real conversation is expected, not just small talk. | R34: Treat an informal coffee/chat invitation from a professional contact as a real opportunity — prepare a few relevant points or questions, same as for a formal meeting.
A35: SC-JS-8-a | B35: JS-8-keep-cv-on-file-soft-rejection | C35: Job search | D35: After an unsuccessful interview the email ends: “We'll keep your CV on file for future opportunities.” | E35: What does that mean? | F35: The process has ended. If you're interested later, follow up in a few months. | G35: It's a polite way to close without an explicit “no”, not a commitment to revisit you. | H35: That they'll contact you when a role comes up. | I35: Don't wait to be contacted. The phrase usually ends that process. | J35: That the decision is still open. | K35: It isn't. Treat this process as over, and follow up yourself if you want future roles. | L35: Approved | M35: Bulk-approved by founder; item review pending | P35: =MAX(LEN(G35),LEN(I35),LEN(K35)) | Q35: This phrase functions as a polite way to end the conversation without an explicit "no," rather than a genuine commitment to revisit the application later. | R35: Treat this phrase as the end of that specific process, and if genuinely interested in future roles, proactively follow up in a few months rather than waiting to be contacted.
A36: SC-JS-12-a | B36: JS-12-finalizing-internally-offer-delay | C36: Job search | D36: After a verbal job offer, the employer says, “We're just waiting on some internal sign-off.” No date is given. | E36: What do you do? | F36: Ask roughly when to expect the formal offer. | G36: Such delays are usually administrative, not a sign the decision is still undecided. | H36: Assume the offer is being withdrawn. | I36: It's most often approvals and paperwork. Anxious guessing doesn't help. | J36: Wait quietly and say nothing. | K36: Asking for a timeframe is fine, and it gets you something concrete. | L36: Approved | M36: Bulk-approved by founder; item review pending | P36: =MAX(LEN(G36),LEN(I36),LEN(K36)) | Q36: This delay is most often administrative (approvals, paperwork) rather than a sign the decision itself is still genuinely undecided. | R36: Ask for a specific timeframe rather than waiting anxiously: "That's great to hear — roughly when should I expect the formal offer through?"
A37: SC-JS-15-a | B37: JS-15-meet-the-team-informal-framing | C37: Job search | D37: Before a final stage you're told, “It's just an informal chat to meet the team, no pressure.” | E37: How do you approach it? | F37: Prepare as for a formal interview, with questions and examples ready. | G37: Team members are usually asked for feedback afterwards, so the chat is genuinely assessed. | H37: Relax completely and go without preparing. | I37: The casual framing is real, but the feedback it produces counts. | J37: Treat it as a pure social event and avoid talking about work. | K37: It's assessed even if it doesn't feel like an interview, so have questions and examples ready. | L37: Approved | M37: Bulk-approved by founder; item review pending | N37: Yes | P37: =MAX(LEN(G37),LEN(I37),LEN(K37)) | Q37: Team members are typically asked for feedback afterward regardless of the casual framing, so the conversation is genuinely assessed even if it doesn't feel like a formal interview. | R37: Prepare for an "informal" meeting stage with the same care as a formal interview — have a few questions and examples ready, even if the tone in the room is relaxed.
A38: SC-SO-3-a | B38: SO-3-queueing-norm-enforcement | C38: Social | D38: In a bakery, a loose group of people stands near the counter. You can't tell whether it's a queue. | E38: What do you do? | F38: Ask, “Sorry, is this the end of the queue?” | G38: It's a completely normal question. Queue order is taken seriously as a matter of fairness. | H38: Walk to the front of the group. | I38: That prompts visible disapproval. Queueing is taken seriously. | J38: Stand nearby and watch to work out who's next. | K38: Asking directly is normal and expected. Guessing risks stepping out of order. | L38: Approved | M38: Bulk-approved by founder; item review pending | P38: =MAX(LEN(G38),LEN(I38),LEN(K38)) | Q38: Queue order is taken seriously as a matter of fairness, and a correction — even a mild one — reflects a real social expectation, not an overreaction. | R38: When uncertain whether a group is queueing, ask directly: “Sorry, is this the end of the queue?” — a completely normal and expected question.
A39: SC-SO-4-a | B39: SO-4-small-talk-weather-function | C39: Social | D39: A shopkeeper says, “Terrible weather we're having, isn't it?” | E39: How do you answer? | F39: Briefly agree: “I know, awful, isn't it!” | G39: It's a greeting ritual to set a friendly tone, not a real question about the weather. | H39: Give your detailed view of the forecast. | I39: A long answer to a ritual remark comes across as oddly serious. | J39: Say nothing, since it isn't really a question. | K39: The reply is part of the greeting. A brief agreement keeps the tone friendly. | L39: Approved | M39: Bulk-approved by founder; item review pending | N39: Yes | P39: =MAX(LEN(G39),LEN(I39),LEN(K39)) | Q39: This is a social ritual to establish a friendly tone, not a genuine request for detailed opinion or information about the weather. | R39: A brief, light agreement (“I know, awful, isn't it!”) is the expected response — treat it as a greeting, not a real question.
A40: SC-SO-5-a | B40: SO-5-punctuality-for-social-events | C40: Social | D40: You're invited to a friend's casual dinner for 7pm. You arrive at exactly 7pm and the host is still cooking. | E40: What would have been better? | F40: Arriving 10 to 15 minutes after the stated time. | G40: For casual home events the time is treated as approximate. Formal and work events are different. | H40: Arriving even earlier, to help. | I40: Earlier makes it worse. Hosts often aren't ready on the dot. | J40: Arriving an hour late, to be safe. | K40: Too far. About 10 to 15 minutes after is the usual margin for a casual invitation. | L40: Approved | M40: Bulk-approved by founder; item review pending | P40: =MAX(LEN(G40),LEN(I40),LEN(K40)) | Q40: For casual social events specifically (not formal or work-related ones), the stated time is often treated as approximate rather than fixed — arriving exactly on time can occasionally catch a host still getting ready. | R40: For clearly informal social invitations, treat the stated time as approximate and consider arriving 10-15 minutes after — though always exactly on time for anything formal or work-related.
A41: SC-SO-6-a | B41: SO-6-lets-do-this-again-closing-phrase | C41: Social | D41: As you part, a new friend says, “We should totally do this again, let's not leave it so long next time.” No date is mentioned. | E41: What do you do? | F41: Suggest a specific time: “Would you be free sometime in the next couple of weeks?” | G41: The feeling is usually genuine, but with no date it isn't a firm plan. | H41: Wait for them to send an invitation. | I41: It may not happen without a specific date. If you're keen, suggest one. | J41: Take it as a polite lie and drop it. | K41: It's usually sincere, just not a plan. A concrete suggestion turns it into one. | L41: Approved | M41: Bulk-approved by founder; item review pending | P41: =MAX(LEN(G41),LEN(I41),LEN(K41)) | Q41: The sentiment is usually genuine as a general feeling, but without a specific date attached, it's not a firm plan and may or may not happen. | R41: If genuinely interested in meeting again, suggest a specific time on the spot or shortly after: "Would you be free sometime in the next couple of weeks?"
A42: SC-SO-7-a | B42: SO-7-round-buying-pub-culture | C42: Social | D42: At the pub a colleague says, “I'll get this round.” Later, as the evening goes on, he looks around the group expectantly. | E42: What do you do? | F42: Offer to buy the next round, even a non-alcoholic one if you prefer. | G42: Rounds are reciprocal. Consistently not taking a turn can be quietly noticed. | H42: Say thanks and let others keep buying. | I42: Letting others buy all evening is noticed, even if nobody says so. | J42: Pay him back for your own drink at the end. | K42: That settles the cost but misses the norm: taking a turn is how you take part. | L42: Approved | M42: Bulk-approved by founder; item review pending | P42: =MAX(LEN(G42),LEN(I42),LEN(K42)) | Q42: This is a reciprocal social norm rather than a one-off generosity; consistently not taking a turn can be quietly noticed, even if never mentioned directly. | R42: Offer to buy a round at a natural point in the evening, even a non-alcoholic one if preferred, to participate in the norm rather than opting out entirely.
A43: SC-SO-9-a | B43: SO-9-emotional-understatement-not-too-bad | C43: Social | D43: You ask a colleague how a big presentation went. They answer, “Not too bad, thanks.” | E43: How do you read it? | F43: It could mean anything. Ask what part felt strongest. | G43: These phrases are used for very good and for difficult outcomes alike. | H43: As lukewarm, so it probably went badly. | I43: The same words are often used for something that went very well. | J43: As proof it went perfectly. | K43: It might have, or it might have been hard. Ask a specific question to find out. | L43: Approved | M43: Bulk-approved by founder; item review pending | P43: =MAX(LEN(G43),LEN(I43),LEN(K43)) | Q43: These phrases don't reliably indicate a mild or lukewarm experience — the same words are often used for situations that were actually very good or quite difficult. | R43: Follow up with a specific question rather than taking a flat understatement at face value: "That's great to hear — what part felt strongest?"
A44: SC-SO-11-a | B44: SO-11-dinner-party-gift-bringing-norm | C44: Social | D44: A friend invites you with: “Come round for dinner on Friday.” Nothing is said about bringing anything. | E44: What do you do? | F44: Bring a small item, such as wine, dessert or flowers. | G44: The expectation is assumed as common knowledge, so it doesn't need to be stated. | H44: Go empty-handed, since nothing was asked. | I44: Most other guests will bring something. Not being asked doesn't mean not expected. | J44: Offer to pay towards the food. | K44: That's more than is expected. A small gift such as wine or flowers is the usual gesture. | L44: Approved | M44: Bulk-approved by founder; item review pending | P44: =MAX(LEN(G44),LEN(I44),LEN(K44)) | Q44: The expectation is assumed as common knowledge rather than stated, so its absence from the invitation doesn't mean it isn't expected. | R44: As a general default, bring a small item (wine, a dessert, flowers) to any home dinner invitation unless the host has explicitly said not to.
A45: SC-SO-13-a | B45: SO-13-deadpan-irony-unflagged | C45: Social | D45: Looking at a chaotic project plan, a colleague says, without a smile, “Oh, that's going well, then.” | E45: How do you take it? | F45: As dry humour. A light “ha, fair enough” works. | G45: Deadpan sarcasm intentionally has no tonal cue. It isn't meant literally. | H45: Literally, and ask what they're worried about. | I45: A remark that contradicts the obvious facts is often dry humour, not information. | J45: As an insult, and take offence. | K45: A straight face is part of the style. A light reply works safely either way. | L45: Approved | M45: Bulk-approved by founder; item review pending | P45: =MAX(LEN(G45),LEN(I45),LEN(K45)) | Q45: The lack of an obvious tonal cue is intentional to the humor style, not a sign the person actually meant the statement literally. | R45: When a statement seems oddly extreme or contradicts the obvious facts, consider it might be dry humor, and a light "ha, fair enough" response works safely either way.
A46: SC-SO-15-a | B46: SO-15-compliment-deflection-response | C46: Social | D46: You tell a colleague, “That presentation was brilliant.” She replies, “Oh, it was nothing, really.” | E46: What do you say next? | F46: A warm restatement: “Well, I thought it was great.” | G46: It's a politeness habit, not a real denial. A brief warm restatement lands well. | H46: Insist on proving it with examples until she agrees. | I46: No need to press. Take the deflection lightly. | J46: Agree that it was nothing special. | K46: She doesn't mean it literally. Taking it literally misses the point. | L46: Approved | M46: Bulk-approved by founder; item review pending | P46: =MAX(LEN(G46),LEN(I46),LEN(K46)) | Q46: This deflection is a social politeness habit rather than a genuine denial that the compliment is deserved or accurate. | R46: A brief, warm restatement usually lands well after a deflection: "Well, I thought it was great" — no need to press further or take the deflection literally.
A47: SC-AB-1-a | B47: AB-1-council-tax-band-query-formality | C47: Admin & bureaucracy | D47: You want to ask the council a quick question. The website offers only a multi-step form or a phone line with a long wait. | E47: What do you do? | F47: Use the form or phone line, and say clearly at the start if it's urgent. | G47: It's the standard way UK councils handle queries, not a sign they don't care. | H47: Keep looking for a direct email address to a person. | I47: A faster informal route usually doesn't exist. The official channel is the expected one. | J47: Give up on the question. | K47: The form works, even for small queries. Note any urgency at the start of the request. | L47: Approved | M47: Bulk-approved by founder; item review pending | P47: =MAX(LEN(G47),LEN(I47),LEN(K47)) | Q47: This is the standard structure of UK local council service delivery, not a sign the council is uninterested in resolving a simple issue quickly. | R47: Use the official form or phone line as the expected channel, and if it's genuinely urgent, note that clearly at the start of the request rather than expecting a faster informal route.
A48: SC-AB-3-a | B48: AB-3-gp-registration-proof-of-address-strictness | C48: Admin & bureaucracy | D48: At a GP registration desk the clerk says, “We can't accept that. It needs to be a utility bill or bank statement from the last three months.” You offered your tenancy agreement. | E48: How do you read this? | F48: As a fixed rule for everyone. Next time, ask in advance which documents are accepted. | G48: It's an institutional rule applied uniformly, not a judgement about you or your case. | H48: As the clerk singling you out. | I48: It's the same for everyone. Asking in advance saves a wasted trip. | J48: As her choice, so ask her to make an exception. | K48: Fixed rules leave staff little discretion. Check the requirements before you go. | L48: Approved | M48: Bulk-approved by founder; item review pending | P48: =MAX(LEN(G48),LEN(I48),LEN(K48)) | Q48: This reflects fixed institutional rules applied uniformly to everyone, not a judgement being made about this specific case. | R48: Ask in advance exactly which documents are accepted before attending in person, to avoid a wasted trip and the frustration of an on-the-spot rejection.
A49: SC-AB-4-a | B49: AB-4-hmrc-letter-response-urgency-mismatch | C49: Admin & bureaucracy | D49: An HMRC letter about a small discrepancy says, “You may be liable for a penalty.” The tone is intimidating. | E49: What do you do? | F49: Read what's actually being asked, and call HMRC to check how urgent it is. | G49: Formal legal wording is used across all HMRC letters, serious or trivial, so tone doesn't show urgency. | H49: Treat it as a serious problem and panic. | I49: The tone alone isn't a guide. Read the actual content and check. | J49: Ignore it, since the wording is just boilerplate. | K49: Don't ignore it either. Read it and call to clarify the real urgency. | L49: Approved | M49: Bulk-approved by founder; item review pending | P49: =MAX(LEN(G49),LEN(I49),LEN(K49)) | Q49: Standardized formal wording is used across the full range of HMRC correspondence, from serious to trivial, so the tone alone shouldn't be used to gauge urgency. | R49: Read the specific factual content (what's actually being asked or stated), and call HMRC directly to clarify actual urgency and next steps rather than reacting to the tone.
A50: SC-AB-5-a | B50: AB-5-visa-immigration-advisor-directness-expectation | C50: Admin & bureaucracy | D50: You ask an immigration advisor, “Is my situation okay?” and get a general, hedged answer: “It depends, generally speaking.” | E50: What do you do? | F50: Ask specific, direct questions, such as exactly which figures or dates are required. | G50: Advisors tend to answer in kind: a specific question gets a specific, more useful answer. | H50: Take the answer as reassurance. | I50: It's a general reply to a general question, not confirmation of your case. | J50: Ask the same broad question again, more firmly. | K50: A narrower question is what gets a specific answer. | L50: Approved | M50: Bulk-approved by founder; item review pending | N50: Yes | P50: =MAX(LEN(G50),LEN(I50),LEN(K50)) | Q50: Professional UK advisors typically respond in kind to how a question is asked — a specific, direct question usually receives a specific, direct, more useful answer. | R50: Ask specific, direct questions (“What exactly is the minimum bank balance required, and for how many days?”) rather than broad ones, to get equally specific answers.
A51: SC-AB-8-a | B51: AB-8-please-allow-28-days-boilerplate | C51: Admin & bureaucracy | D51: An official form says, “Please allow up to 28 days for a response.” You're worried it'll take the full month. | E51: How do you treat the figure? | F51: As an upper limit. Follow up only after the full window has passed. | G51: It's a safety margin covering worst cases, not an average, and replies are often faster. | H51: As the expected wait, so plan around 28 days. | I51: Responses often arrive sooner. It's a maximum. | J51: As a cue to chase after a week. | K51: Chasing before the stated window ends is premature. Wait until it has passed. | L51: Approved | M51: Bulk-approved by founder; item review pending | P51: =MAX(LEN(G51),LEN(I51),LEN(K51)) | Q51: Actual processing is often faster than the stated maximum, since the figure is a safety margin covering worst-case delays, not an average expectation. | R51: Treat the stated window as an upper limit rather than an expected wait, and only follow up once that full window has genuinely passed.
A52: SC-AB-9-a | B52: AB-9-energy-switch-retention-script | C52: Admin & bureaucracy | D52: You try to cancel a broadband contract. The agent says, “Before you go, can I offer you our best available rate?” | E52: What do you do? | F52: Compare it with the new deal, and decline if the new one is better. | G52: It's a standard retention step used broadly, not a special effort because you're valued. | H52: Accept at once, since it must be a special offer. | I52: It's offered routinely. Judge it against your alternative on its own merits. | J52: Feel you have to take it, to be polite. | K52: Declining is fine. A polite “no thanks” works if your other offer is better. | L52: Approved | M52: Bulk-approved by founder; item review pending | P52: =MAX(LEN(G52),LEN(I52),LEN(K52)) | Q52: This is a standard sales retention step applied broadly, not a special effort made only because this particular customer is especially valued. | R52: It's fine to compare the retention offer against the new supplier's deal on its own merits and simply decline if the new offer is still better.
A53: SC-AB-10-a | B53: AB-10-tv-licence-enforcement-letter-tone | C53: Admin & bureaucracy | D53: You don't own a television. A letter arrives: “Our records show no licence is held at this address.” It sounds threatening. | E53: What do you do? | F53: Complete the “no licence needed” declaration on their website. | G53: These letters go to many households and aren't evidence of an investigation into you. | H53: Panic, since they must be investigating you. | I53: They're sent widely, even to people who don't watch broadcast TV. | J53: Ignore it completely. | K53: A short online declaration settles it, so there's no need to worry, and it's easy to do. | L53: Approved | M53: Bulk-approved by founder; item review pending | P53: =MAX(LEN(G53),LEN(I53),LEN(K53)) | Q53: These letters are sent widely and are not evidence of a specific investigation into that individual household's viewing habits. | R53: If no licence is genuinely needed, it's sufficient to complete the standard "no licence needed" declaration on their website rather than worrying further.
A54: SC-AB-12-a | B54: AB-12-school-waiting-list-ack-letter | C54: Admin & bureaucracy | D54: You apply for a nursery place and receive a letter: “Your application has been received and added to our records.” | E54: What does the letter tell you? | F54: Only that it was received. Ask separately where you are on the waiting list. | G54: It's procedural confirmation. Its formal tone says nothing about how soon a place might be offered. | H54: That a place is likely soon. | I54: It doesn't say that. It carries no signal about timing. | J54: That your application has been refused. | K54: It's neutral confirmation. If timing matters, ask directly. | L54: Approved | M54: Bulk-approved by founder; item review pending | P54: =MAX(LEN(G54),LEN(I54),LEN(K54)) | Q54: This letter is purely procedural confirmation, and its formal tone doesn't provide any signal about how likely or soon a place might be offered. | R54: If timing matters, ask directly and separately: "Roughly where would we be on the waiting list, and when might we hear about a place?"
A55: SC-AB-14-a | B55: AB-14-ombudsman-escalation-language | C55: Admin & bureaucracy | D55: A company's final complaint reply ends: “If you're not satisfied, you can refer this to the Ombudsman.” You're still unhappy. | E55: What do you do? | F55: Say plainly: “If this isn't resolved, I'll take it to the ombudsman next.” | G55: Mentioning the ombudsman is a normal, non-confrontational step in the process. | H55: Avoid mentioning it, since that would seem aggressive. | I55: It isn't aggressive. The phrase appears on final replies as standard wording. | J55: Treat the line as a sign your complaint was especially serious. | K55: It's boilerplate on final replies, whatever the complaint. Treat it as an option, not a signal. | L55: Approved | M55: Bulk-approved by founder; item review pending | P55: =MAX(LEN(G55),LEN(I55),LEN(K55)) | Q55: This phrase is often boilerplate required by regulation on every final response letter, regardless of how serious the specific complaint actually was. | R55: Referring to the ombudsman step is a normal, non-confrontational part of the process — it's fine to say plainly: "If this isn't resolved, I'll take it to the ombudsman next."
A56: SC-ED-2-a | B56: ED-2-dissertation-supervisor-email-formality | C56: Education | D56: You sent your dissertation supervisor a detailed question. Two days later you get a reply: two short lines, no greeting, no sign-off. | E56: How do you read the reply? | F56: Take it at face value, and send a specific follow-up if you need more detail. | G56: Brevity reflects time pressure across many students, not a verdict on your question or your work. | H56: Decide your supervisor isn't taking your project seriously. | I56: Short, fast replies usually mean a supervisor with many students, not disinterest in you or your project. | J56: Reply apologising for taking their time, and drop the question. | K56: There's no need to withdraw it. If you need more, ask a specific follow-up or request a short meeting. | L56: Approved | M56: Reviewed and approved by founder | P56: =MAX(LEN(G56),LEN(I56),LEN(K56)) | Q56: Brevity reflects time pressure across many students, not a judgment on the importance of the question or the student's work. | R56: Read brief replies at face value for their content, and if more detail is genuinely needed, ask a specific follow-up or request a short meeting rather than reading disinterest into the length.
A57: SC-ED-3-a | B57: ED-3-extension-request-norm | C57: Education | D57: A coursework deadline is three days away and a difficult month has left you far behind. Your university portal has a clearly signposted “extenuating circumstances” form. | E57: What do you do? | F57: Submit the form as early as you can, with the evidence it asks for. | G57: Using the formal process is routine administration, not an admission of failure. | H57: Push through alone and hand in weaker work rather than ask. | I57: Embarrassment is the usual reason people skip it, but the process exists for exactly this and is treated as normal. | J57: Wait until the deadline has passed, then explain what happened. | K57: The process works best used early, with the required evidence, not after the deadline. | L57: Approved | M57: Reviewed and approved by founder | P57: =MAX(LEN(G57),LEN(I57),LEN(K57)) | Q57: Using the formal process is treated as routine administration, not as an admission of failure or something to be embarrassed about. | R57: If genuinely needed, submit the formal extension request as early as possible with whatever evidence is required, rather than trying to manage alone.
A58: SC-ED-14-a | B58: ED-14-group-project-unequal-contribution-norm | C58: Education | D58: In your group project, one member has done almost nothing. The module handbook mentions a peer-assessment form and says to raise concerns with the tutor if informal resolution fails. The deadline is three weeks away. | E58: What do you do? | F58: Raise it with the tutor, factually and with evidence, well before the deadline. | G58: Universities expect this to happen and plan for it. Raising it factually isn't seen as complaining. | H58: Say nothing so you don't seem difficult, and accept the shared grade. | I58: Staying silent is how a shared grade ends up not reflecting your own effort. | J58: Wait until the work is graded, then complain about the unequal effort. | K58: Too late by then. Raise it well before the final deadline, not after grading. | L58: Approved | M58: Reviewed and approved by founder | P58: =MAX(LEN(G58),LEN(I58),LEN(K58)) | Q58: Universities generally expect and plan for this kind of issue to arise and be raised formally — it isn't treated as a personal or social failure to do so. | R58: Raise unequal contribution with the tutor directly and factually, ideally with some documentation (meeting notes, message logs), well before the final deadline rather than after grading.
A59: SC-ED-1-a | B59: ED-1-seminar-participation-expectation | C59: Education | D59: In a seminar the tutor asks the room an open question and waits. Nobody speaks, and you're waiting politely to be invited. | E59: What do you do? | F59: Prepare one or two points beforehand, and volunteer them early. | G59: Consistent silence reads as not having done the reading, not as politeness. | H59: Keep waiting to be invited to speak. | I59: In seminars, contributing is expected, and silence is read very differently here. | J59: Speak only if the tutor calls on you by name. | K59: By then it's been noticed that you didn't volunteer. Contributing early, even briefly, reads better. | L59: Approved | M59: Bulk-approved by founder; item review pending | P59: =MAX(LEN(G59),LEN(I59),LEN(K59)) | Q59: Consistent silence is interpreted as not having done the reading or not engaging with the material, not as a considerate or humble communication style. | R59: Prepare one or two specific points or questions before each seminar and volunteer them early, since contributing even briefly is read very differently from staying silent.
A60: SC-ED-4-a | B60: ED-4-plagiarism-citation-strictness | C60: Education | D60: Your essay comes back with a high similarity score, and a letter invites you to an academic misconduct meeting. You paraphrased sources without citing them. | E60: What's the lesson? | F60: Learn the required citation style early, and cite paraphrased ideas as well as quotes. | G60: Automated checks don't distinguish intent. Unintentional poor citation can start the same process. | H60: Only direct quotes need citing. | I60: Paraphrased ideas need citing too, or they can still trigger the checks. | J60: Rely on explaining your intentions if it comes up. | K60: Intent isn't distinguished at the automated stage, so the safe route is to cite properly from the start. | L60: Approved | M60: Bulk-approved by founder; item review pending | P60: =MAX(LEN(G60),LEN(I60),LEN(K60)) | Q60: The system doesn't generally distinguish intent at the automated-detection stage — unintentional poor citation practice can still trigger the same formal process as deliberate copying. | R60: Learn the specific citation style required (e.g. Harvard, APA) early and cite even paraphrased ideas, not just direct quotes, to avoid triggering the automated similarity checks.
A61: SC-ED-5-a | B61: ED-5-personal-tutor-checkin-brevity | C61: Education | D61: Your personal tutor has a scheduled 15-minute check-in with standard questions: “How's the course going, any concerns?” You do have a real concern. | E61: What do you do? | F61: Say so directly: “There's actually something I wanted to flag.” | G61: Tutors expect this, and the meeting will extend if needed. | H61: Keep to the standard answers because the slot is short. | I61: The brevity is structural, not a sign the tutor can't help with something specific. | J61: Say nothing now and hope to book a separate meeting later. | K61: A brief check-in doesn't mean there's no time for a concern. Raise it now. | L61: Approved | M61: Bulk-approved by founder; item review pending | P61: =MAX(LEN(G61),LEN(I61),LEN(K61)) | Q61: The brevity is a structural feature of how these meetings are run across many students, not a signal that the tutor isn't available to help with something specific. | R61: Raise a specific concern directly even in a brief check-in: "There's actually something I wanted to flag" — tutors expect this and it will extend the meeting if needed.
A62: SC-ED-11-a | B62: ED-11-sen-support-request-process | C62: Education | D62: You raise a concern about your child's reading difficulties. The school replies with information about a formal assessment pathway, not immediate help. | E62: What do you do? | F62: Start the formal request early, and ask what interim support is available meanwhile. | G62: The formal route is expected and can take time, so starting early and asking about interim support helps. | H62: Take it as a refusal to help. | I62: It's the standard route, not a refusal. Ask about interim support. | J62: Wait to see if things improve before starting it. | K62: The assessment can take time, so starting early matters. | L62: Approved | M62: Bulk-approved by founder; item review pending | P62: =MAX(LEN(G62),LEN(I62),LEN(K62)) | Q62: Universities and schools generally expect and plan for this — a school's SENCo submits a request, the local authority must respond within 6 weeks and reach a decision within 16 weeks, and a formal Education, Health and Care Plan (EHCP) is only issued if the assessment supports it; note that England's SEND system is under active reform as of 2026, with a February 2026 white paper proposing EHCPs be reserved for the most complex needs going forward. | R62: Start the formal assessment request as early as possible given it can take time, and ask directly what interim support, if any, is available while the assessment is pending.
A63: SC-ED-12-a | B63: ED-12-headteacher-escalation-formality | C63: Education | D63: You have an unresolved concern at your child's school. The website lists a complaints procedure: class teacher, head of year, headteacher, governors, each stage in writing. | E63: What do you do? | F63: Follow the stages in order, in writing at each stage. | G63: It's the school's standard escalation process, not a confrontation. | H63: Go straight to the headteacher. | I63: Skipping stages typically gets you sent back to the start. | J63: Raise it only verbally, to keep things friendly. | K63: The procedure expects a written record at each stage. | L63: Approved | M63: Bulk-approved by founder; item review pending | N63: Yes | P63: =MAX(LEN(G63),LEN(I63),LEN(K63)) | Q63: This structured escalation is the school's standard, expected process for any unresolved concern, not an indication that going further is confrontational or unusual. | R63: Follow the published complaints procedure in order and in writing at each stage, since skipping stages typically means being redirected back to the start.
A64: SC-ED-13-a | B64: ED-13-freshers-week-social-pressure | C64: Education | D64: Your flatmates keep saying, “Everyone's going” about every freshers' week event. You're tired and unsure. | E64: What do you do? | F64: Pick a few events you like, and skip the rest. | G64: “Everyone's going” is enthusiastic marketing, not a real obligation. Friend groups form over the following weeks. | H64: Go to every event, so you aren't left out. | I64: Nobody expects it. Most students pick and choose. | J64: Skip all of them, since the groups are decided in week one. | K64: A few you enjoy are still worth it, and groups form over the following weeks, not just in week one. | L64: Approved | M64: Bulk-approved by founder; item review pending | P64: =MAX(LEN(G64),LEN(I64),LEN(K64)) | Q64: The framing is enthusiastic marketing language for the events themselves, not an accurate description of real social obligation or expectation. | R64: Pick a few events that genuinely appeal and skip the rest without concern — most students do the same, and social groups form over the following weeks, not solely in freshers' week.
A65: SC-ED-16-a | B65: ED-16-feedback-on-essay-terse-comments | C65: Education | D65: Your essay comes back with a few brief marginal comments and a short summary. You'd expected paragraphs of feedback. | E65: What do you do? | F65: Ask about a specific unclear comment: “Could you expand on what you meant by this?” | G65: Brevity reflects marking volume, not that your work wasn't read or valued. | H65: Conclude the marker didn't read it properly. | I65: Short comments are standard when a lot of work needs marking. | J65: Ignore the comments, since they're so short. | K65: They're brief but useful, and a specific follow-up question gets you more. | L65: Approved | M65: Bulk-approved by founder; item review pending | P65: =MAX(LEN(G65),LEN(I65),LEN(K65)) | Q65: The brevity is a standard grading practice for managing a large volume of marking, not a sign the work wasn't read carefully or valued. | R65: If a brief comment is unclear, follow up directly and specifically: "Could you expand on what you meant by 'strengthen this section' in the third paragraph?"
A66: SC-DR-1-a | B66: DR-1-texting-pace-not-urgency | C66: Dating & relationships | D66: You had a good first date. You text the next morning and they reply that evening, with no apology and no fuss. It keeps happening. | E66: How do you read the slow replies? | F66: Judge interest by what the messages say and how consistent they are, and ask lightly if you're unsure. | G66: Reply speed isn't treated as a strong signal of interest here. A relaxed pace is normal. | H66: Assume they've lost interest, and stop replying yourself. | I66: That's the common mistake: the other person is often just not in the habit of texting quickly. | J66: Time every reply and read the gaps as signals. | K66: Busyness and a relaxed pace are both normal, so the gaps alone tell you very little. | L66: Approved | M66: Reviewed and approved by founder | P66: =MAX(LEN(G66),LEN(I66),LEN(K66)) | Q66: Response speed is not treated as a strong signal of interest the way it might be in some other dating cultures — busyness and a more relaxed pace are both genuinely normal. | R66: Judge interest by the content and consistency of messages over time rather than reply speed alone, and it's fine to ask directly if genuinely unsure: "Just checking we're both still keen on this!"
A67: SC-DR-2-a | B67: DR-2-lets-see-where-this-goes-ambiguity | C67: Dating & relationships | D67: A few dates in, you ask where things stand. They smile and say: “Let's just see where this goes.” | E67: What do you do with that? | F67: Take it as genuine openness, and if you want clarity, ask a more specific question later. | G67: It usually reflects a real preference for not over-defining things early, not hidden reluctance about you. | H67: Treat it as a soft rejection and back away. | I67: That's the misreading. In this context it's meant literally, as openness without a label yet. | J67: Push for a definite answer on the spot. | K67: The phrase asks for room. If clarity matters, ask something more specific later, such as how they feel about where things are. | L67: Approved | M67: Reviewed and approved by founder | P67: =MAX(LEN(G67),LEN(I67),LEN(K67)) | Q67: This phrase usually reflects a real preference for not over-defining things early on, rather than a hidden reluctance specifically about this person. | R67: If clarity matters, ask a more specific question later on rather than reading a fixed meaning into the phrase itself: "How are you feeling about where things are at the moment?"
A68: SC-DR-11-a | B68: DR-11-declining-a-second-date-vague-language | C68: Dating & relationships | D68: After a first date they message: “Really enjoyed meeting you, let's stay in touch!” Neither of you has suggested a second date. | E68: You'd like to see them again. What do you do? | F68: Propose something specific: “I'd love to see you again. Are you free next week sometime?” | G68: With no specific plan proposed, this phrase usually works as a gentle decline, so a concrete invitation is how you show interest. | H68: Reply “Sounds good, let's stay in touch!” and leave it open. | I68: Echoing it leaves nothing arranged. The phrase is usually a polite way of ending things, not an invitation. | J68: Wait a few weeks for them to suggest a second date. | K68: Waiting is the common mistake. The phrase is usually a gentle decline, not a promise to arrange something later. | L68: Approved | M68: Reviewed and approved by founder | P68: =MAX(LEN(G68),LEN(I68),LEN(K68)) | Q68: Without a specific next date proposed, this phrase usually functions as a gentle decline rather than a genuine open-ended invitation to arrange something later. | R68: If genuinely interested in a second date, propose something specific rather than waiting: "I'd love to see you again — are you free next week sometime?"
A69: SC-DR-6-a | B69: DR-6-exclusivity-conversation-directness-expected | C69: Dating & relationships | D69: You've been on several good dates. Nobody has talked about seeing other people. | E69: What do you do? | F69: Raise it directly: “I'd like to talk about whether we're seeing other people.” | G69: Without an explicit conversation, exclusivity can't safely be assumed, however it feels. | H69: Assume you're exclusive, since it feels that way. | I69: Neither person can safely assume it until it's discussed. | J69: Wait for them to bring it up. | K69: It may not come up. Raising it directly once it feels relevant is the usual way. | L69: Approved | M69: Bulk-approved by founder; item review pending | P69: =MAX(LEN(G69),LEN(I69),LEN(K69)) | Q69: Without an explicit conversation, exclusivity is not safely assumed by either person, regardless of how the relationship might feel emotionally. | R69: Raise the exclusivity question directly once it feels relevant, rather than assuming: "I'd like to talk about whether we're seeing other people or not."
A70: SC-DR-7-a | B70: DR-7-ghosting-normalized-explanation | C70: Dating & relationships | D70: After a few good dates their messages stop. There's no explanation, and a week goes by. | E70: What do you do? | F70: Treat it as closed, and move on without chasing an explanation. | G70: It's usually more about avoiding a difficult conversation than a verdict on you. | H70: Keep messaging until they explain. | I70: After about a week with no reply, chasing for closure rarely helps. It's fine to move on. | J70: Decide you must have done something wrong. | K70: It's frequently about the other person's avoidance, not a specific judgement about you. | L70: Approved | M70: Bulk-approved by founder; item review pending | P70: =MAX(LEN(G70),LEN(I70),LEN(K70)) | Q70: While painful, this pattern is frequently more about the other person's avoidance of a difficult conversation than a specific, considered judgment about the recipient. | R70: After a reasonable window with no response (roughly a week for an active connection), it's fine to treat it as a closed situation and move on, rather than continuing to seek an explanation.
A71: SC-DR-8-a | B71: DR-8-breakup-softening-language | C71: Dating & relationships | D71: They end things with: “It's not you, it's me. I just need to focus on myself.” You'd like more detail. | E71: What do you do? | F71: Accept it, and ask only practical questions, such as logistics or mutual friends. | G71: It's a convention for ending things with minimal conflict. Pressing for more usually doesn't help. | H71: Press for a fuller, more literal explanation. | I71: Pushing for a complete emotional account usually isn't productive. | J71: Take the words literally and ask how you can help them. | K71: The phrase isn't meant literally. It's a softened way to end things. | L71: Approved | M71: Bulk-approved by founder; item review pending | P71: =MAX(LEN(G71),LEN(I71),LEN(K71)) | Q71: These phrases are a social convention for ending things with minimal conflict, and pressing for a more literal or complete explanation usually isn't productive. | R71: It's usually more constructive to accept a softened explanation and ask only genuinely practical questions (logistics, mutual friends) rather than pushing for a fuller emotional account.
A72: SC-DR-10-a | B72: DR-10-dating-app-messaging-norm | C72: Dating & relationships | D72: On a dating app a match opens with a short message: “Loved the photo from Cornwall!” You'd expected something longer. | E72: How do you read it? | F72: Judge by how the conversation develops, not by the first message's length. | G72: Length and effort of a first message aren't strongly linked to genuine interest. | H72: As low interest, so don't reply. | I72: A short opener referencing your profile is normal. | J72: As proof they're keener than someone who writes more. | K72: Length says little about interest either way. Let the conversation show it. | L72: Approved | M72: Bulk-approved by founder; item review pending | P72: =MAX(LEN(G72),LEN(I72),LEN(K72)) | Q72: Message length and effort on a first contact are not strongly correlated with how genuinely interested someone actually is once a conversation develops. | R72: Respond based on how the conversation actually develops rather than judging by the length or effort of the very first message.
A73: SC-DR-12-a | B73: DR-12-house-party-flirting-norm | C73: Dating & relationships | D73: At a house party someone spends the evening chatting and teasing you, and keeps ending up near you. Nothing is said about interest. | E73: How do you read it? | F73: As possible interest. If you're unsure, ask lightly: “Should we swap numbers?” | G73: Sustained attention and banter are often how interest is signalled, without a direct statement. | H73: As nothing, since nobody said they like you. | I73: No explicit statement doesn't mean no interest. | J73: As clear proof, so declare how you feel straight away. | K73: It isn't proof either. A light, low-pressure question is the safe way to find out. | L73: Approved | M73: Bulk-approved by founder; item review pending | N73: Yes | P73: =MAX(LEN(G73),LEN(I73),LEN(K73)) | Q73: The absence of an explicit, direct statement of interest doesn't mean interest isn't present — it's often being signaled through sustained attention and banter instead. | R73: Notice sustained attention and playful teasing as potential interest signals in themselves, and it's fine to test the waters with a direct, low-pressure question if unsure: "Should we swap numbers?"
A74: SC-DR-14-a | B74: DR-14-partners-friends-approval-indirectness | C74: Dating & relationships | D74: Your friends are polite to your new partner but a little less warm than usual. Nobody says anything negative. | E74: How do you read it? | F74: As a possible signal. Ask a close friend privately for their honest impression. | G74: No negative comment doesn't necessarily mean full approval. Unstated coolness can be a real signal. | H74: As approval, since nobody objected. | I74: Politeness isn't the same as approval. | J74: As all in your head, so ignore it. | K74: It may be a real signal. A private question to a trusted friend settles it. | L74: Approved | M74: Bulk-approved by founder; item review pending | P74: =MAX(LEN(G74),LEN(I74),LEN(K74)) | Q74: The absence of an openly negative comment doesn't necessarily mean full approval — a noticeable but unstated coolness can be a real, if indirect, signal. | R74: If reading the group's reaction genuinely matters, ask a trusted close friend directly and privately for their honest impression, rather than relying on the group's general politeness as a signal.
A75: SC-DR-16-a | B75: DR-16-meeting-the-family-formal-occasion | C75: Dating & relationships | D75: Your partner says, “Come for Sunday lunch and meet everyone.” It sounds casual. | E75: How do you treat the invitation? | F75: As a meaningful occasion. Prepare, with a small gift and suitable dress. | G75: Sunday lunch is often chosen deliberately for this milestone, whatever the tone of the invitation. | H75: As a casual meal, so turn up as you are. | I75: It carries more weight than a casual visit. | J75: As too much, too soon, so decline politely. | K75: Declining isn't needed. It's an invitation into their family life, worth preparing for. | L75: Approved | M75: Bulk-approved by founder; item review pending | P75: =MAX(LEN(G75),LEN(I75),LEN(K75)) | Q75: This specific setting is often chosen deliberately as the occasion for this milestone, rather than being simply the next convenient time to visit. | R75: Treat a Sunday lunch family invitation as a meaningful occasion worth preparing for (a small gift, appropriate dress), even if the invitation itself sounds casual.
A76: SC-MN-3-a | B76: MN-3-splitting-bill-evenly-default | C76: Money & transactions | D76: At a casual group dinner someone says, “Shall we just split it evenly?” You only had a starter. The others had three courses. | E76: What do you do? | F76: Say lightly: “I only had a starter, would you mind if I paid a bit less?” | G76: That's a normal, unremarkable thing to say when it's said plainly and lightly. | H76: Stay quiet so you don't seem petty, and pay an even share. | I76: Raising it isn't petty. Staying quiet leaves you paying for food you didn't order. | J76: Insist that everyone itemises the bill line by line. | K76: The even split is a casual convenience default. A light word is enough, with no formal itemising. | L76: Approved | M76: Reviewed and approved by founder | P76: =MAX(LEN(G76),LEN(I76),LEN(K76)) | Q76: This default reflects convenience and a general social ease around small imbalances, rather than an expectation that everyone calculate their exact share. | R76: It's entirely acceptable to say plainly and lightly: "I only had a starter, would you mind if I paid a bit less?" — this is a normal, unremarkable thing to raise.
A77: SC-MN-4-a | B77: MN-4-salary-discussion-taboo | C77: Money & transactions | D77: Over coffee you ask a new colleague, “So what do you earn?” They smile and say, “Oh, I do alright.” | E77: What's going on? | F77: Pay is private, so it's a polite deflection. For a benchmark, talk about ranges or market rates instead. | G77: It's a strong general norm, not evasiveness aimed at you. Asking directly was the misstep. | H77: They don't trust you personally. | I77: It isn't aimed at you. Reticence about salary is shared even among close colleagues and friends. | J77: They're being modest, so ask again for the real figure. | K77: Asking again would deepen the misstep. Frame pay around a range or market rate, not a personal question. | L77: Approved | M77: Reviewed and approved by founder | P77: =MAX(LEN(G77),LEN(I77),LEN(K77)) | Q77: This reticence is a strong general cultural norm rather than evasiveness aimed at the specific person asking — a UK survey (Indeed, 7,000+ workers) found 87% of employees uncomfortable asking a colleague their salary and 84% unwilling to share their own, with only 16% comfortable discussing pay with colleagues at all. | R77: Avoid asking directly about someone's salary; if the topic is genuinely relevant (e.g. negotiating a role), frame it around a range or market rate rather than a personal question.
A78: SC-MN-10-a | B78: MN-10-treating-someone-no-expectation-of-repayment | C78: Money & transactions | D78: A friend pays for your drinks and says, “Don't worry about it, I've got this.” You feel uncomfortable owing them. | E78: What do you do? | F78: Say a simple thank you, and treat them back naturally another time. | G78: “I've got this” is a closed gesture, not the start of a tally to be evened out. | H78: Insist on paying them back on the spot. | I78: That tends to feel slightly awkward to the friend, who didn't mean it to be repaid. | J78: Keep track of it as a debt to settle soon. | K78: It isn't an informal debt. Thank them, and reciprocate naturally another time. | L78: Approved | M78: Reviewed and approved by founder | P78: =MAX(LEN(G78),LEN(I78),LEN(K78)) | Q78: This is intended as a straightforward, closed gesture rather than the start of an ongoing tally between friends that needs to be evened out. | R78: Accept the gesture graciously with a simple thank you, and reciprocate naturally another time rather than insisting on immediate repayment.
A79: SC-MN-1-a | B79: MN-1-tipping-optional-modest-norm | C79: Money & transactions | D79: You've paid for a coffee at a café counter. Nobody prompts you to tip. | E79: What do you do? | F79: Don't tip. It isn't expected at counters. | G79: Not tipping in everyday settings like cafés and takeaways is genuinely normal, not rude. | H79: Tip a large amount to be safe. | I79: Not needed. Tipping isn't expected at counters, cafés or most takeaways. | J79: Feel embarrassed and apologise for not tipping. | K79: There's nothing to apologise for. Not tipping here is normal. | L79: Approved | M79: Bulk-approved by founder; item review pending | P79: =MAX(LEN(G79),LEN(I79),LEN(K79)) | Q79: Not tipping in many everyday settings (cafes, takeaways, taxis) is genuinely normal and not read as rude, unlike in some tipping-heavy cultures. | R79: Tip around 10-12.5% at sit-down restaurants if service isn't already included, and don't feel obligated to tip at counters, cafes, or most takeaways.
A80: SC-MN-2-a | B80: MN-2-service-charge-auto-added-notice | C80: Money & transactions | D80: At a restaurant your bill includes a “discretionary service charge” added automatically. The service was fine. | E80: What do you do? | F80: Pay it. If service was poor, you can politely ask for it to be reduced. | G80: In most cases it's fine to pay the standard charge. A polite request is acceptable if service was poor. | H80: Refuse to pay it, since it says discretionary. | I80: “Discretionary” doesn't mean you should refuse. Paying is normal when service was fine. | J80: Pay it and add a large tip on top. | K80: The charge is already for service, so a further tip isn't needed. | L80: Approved | M80: Bulk-approved by founder; item review pending | P80: =MAX(LEN(G80),LEN(I80),LEN(K80)) | Q80: Since the Employment (Allocation of Tips) Act 2023 came into force on 1 October 2024, staff are legally entitled to 100% of tips and service charges with no employer deductions — so despite being labelled "discretionary," the charge is now guaranteed by law to reach staff, which most diners still don't know. | R80: It's fine to simply pay the standard service charge in most cases; if service was genuinely poor, it's acceptable to politely ask for it to be removed or reduced.
A81: SC-MN-5-a | B81: MN-5-borrowing-money-awkwardness-indirect-language | C81: Money & transactions | D81: A friend messages: “This is really awkward to ask, but could you lend me £50?” They hedge heavily. | E81: How do you read the hedging? | F81: As shared discomfort about money, not a crisis. Answer the request plainly. | G81: The hedging is a social convention. It doesn't mean the request is unusual. | H81: As a sign something is seriously wrong. | I81: Awkward framing is common and doesn't signal a bigger problem. | J81: As a sign you must say yes. | K81: You can agree or decline plainly. The awkward framing doesn't oblige you. | L81: Approved | M81: Bulk-approved by founder; item review pending | N81: Yes | P81: =MAX(LEN(G81),LEN(I81),LEN(K81)) | Q81: The hedging reflects a real, broadly shared discomfort around money between friends, not a sign that the specific request is unusually large or inappropriate. | R81: Respond to the practical request itself rather than reading deep concern into the awkward framing, and it's fine to agree or decline plainly either way.
A82: SC-MN-6-a | B82: MN-6-whos-paying-ambiguity-group-meal | C82: Money & transactions | D82: When the bill arrives at a group meal, someone reaches for it slightly first and people exchange glances. Nobody says anything. | E82: What do you do? | F82: Suggest resolving it: “Shall we just split it?” | G82: It's a normal, low-stakes pause. Naming it is well received. | H82: Wait silently until someone gives in. | I82: It usually gets resolved quickly, but taking the initiative is welcome. | J82: Grab the bill and pay for everyone. | K82: That isn't needed. A simple suggestion to split resolves it. | L82: Approved | M82: Bulk-approved by founder; item review pending | P82: =MAX(LEN(G82),LEN(I82),LEN(K82)) | Q82: This ambiguity is a normal, low-stakes social moment rather than a genuine standoff — someone usually resolves it quickly with a suggestion to split or a offer to get it this time. | R82: If the pause feels uncomfortable, it's fine to simply suggest resolving it directly: "Shall we just split it?" — taking the initiative to name it is well received.
A83: SC-MN-9-a | B83: MN-9-fixed-price-no-haggling-norm | C83: Money & transactions | D83: In a high-street shop you like a jacket with a clear price tag. | E83: What do you do? | F83: Treat the price as fixed: pay it, or leave it. | G83: Haggling in standard UK shops is unusual. Flexibility is mainly found at markets or secondhand sales. | H83: Offer a lower price. | I83: Staff generally don't expect it, and it can make the exchange awkward. | J83: Ask for a discount because you're a new customer. | K83: Marked prices are generally fixed. Negotiating mainly belongs to markets or private sales. | L83: Approved | M83: Bulk-approved by founder; item review pending | N83: Yes | P83: =MAX(LEN(G83),LEN(I83),LEN(K83)) | Q83: Attempting to negotiate the price in a standard UK shop is unusual and can create an awkward interaction, rather than being read as normal, expected behavior. | R83: Treat marked prices as fixed in standard retail settings; genuine flexibility mainly exists at some markets, car dealerships, or when buying secondhand items directly from an individual.
A84: SC-MN-11-a | B84: MN-11-charity-doorstep-direct-debit-solicitation | C84: Money & transactions | D84: A street fundraiser in branded clothing says, “Have you got two minutes?” and holds up a tablet. | E84: What do you do? | F84: Say “not today, thanks” and keep walking. | G84: A brief, polite no is completely normal and enough. | H84: Stop and explain in detail why you can't donate. | I84: No explanation is needed. It's a standard approach, not a personal ask. | J84: Feel you have to listen for two minutes. | K84: You don't. A short polite refusal while walking is normal. | L84: Approved | M84: Bulk-approved by founder; item review pending | P84: =MAX(LEN(G84),LEN(I84),LEN(K84)) | Q84: This is a standard, widely used charity fundraising approach rather than a sign of a specific, unusually aggressive or targeted ask. | R84: A brief, polite "not today, thanks" while continuing to walk is a completely normal and sufficient response to a street fundraiser.
A85: SC-MN-12-a | B85: MN-12-arranged-vs-unarranged-overdraft-terminology | C85: Money & transactions | D85: Your bank app says you've gone into an “unarranged overdraft”. You worry it means you've done something wrong. | E85: What does it mean, and what do you do? | F85: It's standard terminology. If you'll need an overdraft, ask for an arranged limit in advance. | G85: It's precise banking terminology, not a warning about your behaviour. | H85: That you're being accused of wrongdoing. | I85: It's just a term for borrowing beyond an agreed limit. | J85: That it's the same as arranged, so there's nothing to do. | K85: Not quite. Asking for an arranged limit in advance generally means lower fees. | L85: Approved | M85: Bulk-approved by founder; item review pending | P85: =MAX(LEN(G85),LEN(I85),LEN(K85)) | Q85: This is precise, standard banking terminology rather than a personal warning about financial behaviour — since April 2020, an unarranged overdraft no longer costs noticeably more than an arranged one (both use the same rate), so the real risk is simply not knowing a limit was agreed, or exceeding it, rather than a punitive fee difference. | R85: Ask the bank directly to set up an arranged overdraft limit in advance if overdraft use is likely, since this generally comes with lower fees than going into an unarranged one unexpectedly.
A86: SC-TR-1-a | B86: TR-1-delay-repay-compensation-claim-norm | C86: Transport & commuting | D86: Your train arrives 40 minutes late. No refund appears and nobody mentions compensation. | E86: What do you do? | F86: Check your operator's Delay Repay process online and submit a claim with your ticket details. | G86: The scheme is real, but it relies on you claiming. For most tickets, nothing is issued automatically. | H86: Assume nothing can be done and move on. | I86: Many passengers don't realise they're entitled to compensation. After a long delay, check your operator's rules. | J86: Wait for the money to arrive automatically. | K86: It won't. The system relies entirely on the passenger noticing and submitting a claim. | L86: Approved | M86: Reviewed and approved by founder | P86: =MAX(LEN(G86),LEN(I86),LEN(K86)) | Q86: This is a deliberate, genuinely used compensation scheme (thresholds and payout tiers vary slightly by operator), but the system relies entirely on the passenger noticing and submitting a claim within 28 days of the journey — nothing is issued automatically for most tickets. | R86: After any delay of 15 minutes or more, check the specific train operator's Delay Repay claim process online and submit a claim with the ticket and journey details.
A87: SC-TR-2-a | B87: TR-2-quiet-coach-etiquette | C87: Transport & commuting | D87: You're on a phone call on a train when a passenger gives you a long, pointed look. Then you notice the “Quiet Coach” sign above the seats. | E87: What do you do? | F87: End the call, and take any call in the vestibule or another carriage. | G87: The quiet coach is enforced by fellow passengers as much as by staff, and it's meant seriously. | H87: Lower your voice and carry on, since no staff have said anything. | I87: Staff aren't needed. Passengers enforce this carriage themselves, and the expectation is strong. | J87: Ignore the look. It's just one unfriendly person. | K87: The look is the signal. Visible disapproval, even without a word, reflects a shared expectation. | L87: Approved | M87: Reviewed and approved by founder | P87: =MAX(LEN(G87),LEN(I87),LEN(K87)) | Q87: The social enforcement in this specific carriage is taken seriously even without staff present, reflecting a genuinely strong shared expectation, not just a suggestion. | R87: Check for quiet coach signage when boarding, and move to a vestibule or another carriage for any call, even a short one, if seated in a quiet coach.
A88: SC-TR-8-a | B88: TR-8-excuse-me-this-is-my-stop-navigating-crowd | C88: Transport & commuting | D88: The bus is packed and your stop is next. Standing passengers are between you and the door. | E88: What do you do? | F88: Say “excuse me, this is my stop” clearly a stop or two ahead, so people can move. | G88: A spoken request, made early, is the expected way, and people usually move aside promptly. | H88: Squeeze through without saying anything. | I88: Pushing past without speaking first is more likely to be read as rude. | J88: Wait until the doors are about to open, then ask. | K88: That leaves people no time to move. Ask a stop or two ahead. | L88: Approved | M88: Reviewed and approved by founder | P88: =MAX(LEN(G88),LEN(I88),LEN(K88)) | Q88: This verbal request is treated as sufficient and expected — physically pushing past without speaking first is more likely to be read as rude. | R88: Say "excuse me, this is my stop" clearly a stop or two in advance to give people time to move, rather than waiting until the doors are about to open.
A89: SC-TR-3-a | B89: TR-3-give-up-seat-norm | C89: Transport & commuting | D89: You're seated on a crowded train when someone with a “Baby on board” badge gets on. Other passengers are already glancing around. | E89: What do you do? | F89: Offer your seat straight away, without waiting to be asked. | G89: It's a firm, widely shared expectation, and passengers nearby notice if it isn't met. | H89: Wait to be asked, so you don't presume. | I89: People rarely ask. Offering proactively is expected. | J89: Assume someone else will offer. | K89: Others are watching. If you're closest, the expectation falls on you. | L89: Approved | M89: Bulk-approved by founder; item review pending | P89: =MAX(LEN(G89),LEN(I89),LEN(K89)) | Q89: This is treated as a firm, widely shared social expectation rather than an optional courtesy, and failing to act on it is noticed by others nearby. | R89: Stay alert to fellow passengers who may need a seat (elderly, visibly pregnant, using a mobility aid) and offer proactively rather than waiting to be asked.
A90: SC-TR-4-a | B90: TR-4-escalator-standing-side-norm | C90: Transport & commuting | D90: You step onto a busy station escalator and stand on the left. People behind you sigh and say “excuse me”. | E90: What was the mistake? | F90: On busy escalators, stand on the right and keep the left clear for walkers. | G90: In busy commuting periods it's treated as a near-firm rule, not a loose suggestion. | H90: Nothing. Everyone should be able to stand where they like. | I90: The sighs are the signal. The convention is stronger than it looks. | J90: You should have been walking up too. | K90: No, standing is fine. Just on the right, leaving the left clear for walkers. | L90: Approved | M90: Bulk-approved by founder; item review pending | P90: =MAX(LEN(G90),LEN(I90),LEN(K90)) | Q90: This is treated as a near-firm rule in practice, not a loose suggestion, particularly during busy commuting periods. | R90: Default to standing on the right on any escalator in a busy transport hub, keeping the left clear for people who want to walk.
A91: SC-TR-5-a | B91: TR-5-staff-apology-on-behalf-of-delay | C91: Transport & commuting | D91: A conductor says, “I'm so sorry about the delay.” It was caused by a signal failure elsewhere. | E91: How do you take that? | F91: As a standard courtesy. Ask for an update if you need practical information. | G91: It's a scripted courtesy, not the staff member taking personal responsibility. | H91: As proof the conductor caused it personally. | I91: It's a standard courtesy for delays from any cause. | J91: As a promise the delay will be short. | K91: It says nothing about length. Ask: “Do you have any update on how long it might be?” | L91: Approved | M91: Bulk-approved by founder; item review pending | P91: =MAX(LEN(G91),LEN(I91),LEN(K91)) | Q91: This is a scripted, standard customer service courtesy rather than the individual staff member taking personal responsibility for the cause of the delay. | R91: Accept the apology as standard courtesy and, if practical information is genuinely needed, ask directly: "Do you have any update on how long the delay might be?"
A92: SC-TR-6-a | B92: TR-6-bus-request-stop-hand-signal | C92: Transport & commuting | D92: You wait at a bus stop without raising your hand. The bus drives straight past. | E92: What should you have done? | F92: Raised a hand clearly as it approached. | G92: At request stops, buses may not stop unless someone signals. | H92: Waited closer to the road. | I92: Position isn't the signal. A raised hand is. | J92: Assumed the driver missed you, and complained. | K92: It wasn't an error. Not stopping automatically is standard at request stops. | L92: Approved | M92: Bulk-approved by founder; item review pending | N92: Yes | P92: =MAX(LEN(G92),LEN(I92),LEN(K92)) | Q92: The bus not stopping automatically at every stop is standard operating procedure at request stops, not an error or the driver missing the passenger. | R92: Raise a hand clearly as the bus approaches any stop that might be a request stop, rather than assuming the bus will stop automatically.
A93: SC-TR-7-a | B93: TR-7-tap-in-tap-out-contactless-fare-norm | C93: Transport & commuting | D93: You've been charged the maximum fare for a journey because you forgot to tap out with your contactless card. | E93: What do you do? | F93: Submit a fare correction request online with the journey details. | G93: A missed tap-out gets the maximum fare automatically, and it isn't necessarily refunded without a request. | H93: Assume it's an error that will fix itself. | I93: It's an automatic rule, and a refund needs a specific request. | J93: Accept the charge as a penalty. | K93: It can be corrected. Submit the request, and tap out on every journey from now on. | L93: Approved | M93: Bulk-approved by founder; item review pending | P93: =MAX(LEN(G93),LEN(I93),LEN(K93)) | Q93: The maximum fare charge for a missed tap-out is an automatic system rule applied uniformly, not a targeted penalty or an error that will necessarily be refunded without a specific request. | R93: Always tap out at the end of every journey, and if a maximum fare is mistakenly charged, submit a fare correction request online with the specific journey details.
A94: SC-TR-12-a | B94: TR-12-road-rage-passive-restrained-norm | C94: Transport & commuting | D94: On the road another driver gives a brief flash of headlights after you pull out. They don't honk or follow you. | E94: How do you respond? | F94: Take it as mild, passing frustration. Give a small wave or nod. | G94: It's a clear but contained signal, not an invitation to escalate. | H94: As an aggressive challenge, and confront them. | I94: That's the common misreading. Responding calmly lets it end there. | J94: As a friendly greeting. | K94: It's mild frustration, not a greeting. A small wave or nod acknowledges it. | L94: Approved | M94: Bulk-approved by founder; item review pending | N94: Yes | P94: =MAX(LEN(G94),LEN(I94),LEN(K94)) | Q94: These are understood as clear but contained frustration signals within the driving culture, not an invitation to escalate into a direct confrontation. | R94: Read a brief horn tap or headlight flash as mild, passing frustration rather than an escalation, and respond calmly (a small wave or nod) rather than engaging further.
A95: SC-TR-17-a | B95: TR-17-first-class-carriage-informal-enforcement | C95: Transport & commuting | D95: The train is quiet and first class is empty, so you sit there with a standard ticket. The conductor says politely, “This is a first-class carriage. Would you like to upgrade or move to standard?” | E95: What do you do? | F95: Move promptly. It's consistently enforced, however empty it looks. | G95: It's a genuine rule, enforced regardless of how empty first class appears. | H95: Explain that nobody else is using it. | I95: The empty seats don't change the rule. It's enforced regardless. | J95: Stay put, since the request was polite. | K95: Polite doesn't mean optional. Move to the correct carriage when asked. | L95: Approved | M95: Bulk-approved by founder; item review pending | P95: =MAX(LEN(G95),LEN(I95),LEN(K95)) | Q95: This is treated as a genuine, consistently enforced rule rather than a loose guideline that depends on how busy the train happens to be. | R95: Check ticket class before sitting down, and move to the correct carriage promptly if asked, since this is consistently enforced regardless of how empty first class appears.
A96: SC-NB-2-a | B96: NB-2-garden-hedge-boundary-etiquette | C96: Neighbours & community | D96: Your neighbour catches you in the garden and says lightly, “The hedge is getting a bit tall on our side, whenever you get a chance.” | E96: How do you take that? | F96: As a genuine request. Deal with the hedge soon. | G96: This casual approach is the expected first step. It's polite, but it is a request. | H96: As small talk that needs no action. | I96: The light wording is how the request is made. Ignoring it can lead to something more formal. | J96: Wait for a formal letter before doing anything. | K96: Formal steps only come if the casual approach changes nothing, so waiting for one means missing the actual request. | L96: Approved | M96: Reviewed and approved by founder | P96: =MAX(LEN(G96),LEN(I96),LEN(K96)) | Q96: This indirect first approach is the expected initial step — escalating quickly to something formal without first raising it casually can come across as overly confrontational. | R96: Raise a boundary or hedge issue casually and lightly with a neighbour directly first, and reserve anything more formal for if the casual approach doesn't lead to any change.
A97: SC-NB-8-a | B97: NB-8-parking-outside-someones-house-etiquette | C97: Neighbours & community | D97: You've parked outside the same house most days. The neighbour smiles as you walk past and says: “Oh, I see you've found our spot!” | E97: What does that mean? | F97: A pointed, indirect hint. Avoid parking there regularly. | G97: There's no legal claim to the space, but a strong informal expectation that residents respect. | H97: A friendly welcome to the street. | I97: The smile is polite, but the comment is a quiet complaint. | J97: A warning that you're breaking the law. | K97: No law is broken. It's an informal expectation, which is why it comes as a hint. | L97: Approved | M97: Reviewed and approved by founder | P97: =MAX(LEN(G97),LEN(I97),LEN(K97)) | Q97: There's no legal entitlement to the space directly outside one's own house, but there's a strong informal social expectation around it that residents generally respect anyway. | R97: Where possible, avoid consistently parking directly outside a specific neighbour's house, even where legally permitted, to avoid this common source of quiet friction.
A98: SC-NB-14-a | B98: NB-14-loud-music-unwritten-curfew-hours | C98: Neighbours & community | D98: It's gone 11:30 on a weeknight and your music is at a normal volume. There's a polite knock: “Sorry to bother you, just wondering if you could turn the music down a bit.” | E98: What do you do? | F98: Turn it down now, and keep noise down by around 11pm on weeknights from then on. | G98: The curfew is unwritten but widely observed, and enforced socially. | H98: Point out that no rule says you have to. | I98: No written rule doesn't mean no expectation. This one is genuinely widely observed. | J98: Turn it down a little and carry on. | K98: A polite knock like this is pointed. The expectation is real, even if nobody states a rule. | L98: Approved | M98: Reviewed and approved by founder | P98: =MAX(LEN(G98),LEN(I98),LEN(K98)) | Q98: The absence of a written rule doesn't mean there's no real expectation — this unwritten curfew is genuinely, widely observed and enforced socially. | R98: As a general default, keep noise down by around 11pm on weeknights (a bit later at weekends), even with no explicit rule stated, to avoid this common source of neighbourly friction.
A99: SC-NB-1-a | B99: NB-1-bin-collection-day-strictness | C99: Neighbours & community | D99: You put your bin out on the wrong day. It's left uncollected with a small sticker and no personal note. | E99: How do you read it? | F99: As the standard council process. Check the collection calendar for your exact address. | G99: The lack of a personal warning reflects scale and standard process, not you being targeted. | H99: As a neighbour complaining about you. | I99: It's the council's process, not a personal complaint. | J99: As a mistake to ignore, since bins get collected eventually. | K99: Collection days vary by street and change with holidays. Check your own calendar. | L99: Approved | M99: Bulk-approved by founder; item review pending | P99: =MAX(LEN(G99),LEN(I99),LEN(K99)) | Q99: The lack of a direct, personal warning reflects the scale and standard process of council waste collection, not a decision specifically targeting that household. | R99: Check the specific council collection calendar for the exact address, since bin days and which bin is collected can vary street by street and change with public holidays.
A100: SC-NB-3-a | B100: NB-3-neighbourhood-facebook-group-norms | C100: Neighbours & community | D100: In the neighbourhood Facebook group you post a strongly worded opinion on a local political issue. Cool comments appear, and an admin removes the post. | E100: What does that tell you? | F100: The group has unwritten norms. Observe its tone before posting opinions. | G100: These norms are informal but really enforced, and off-topic posts draw a cool response. | H100: The admin is being unfair, so repost it. | I100: The norms are informal but real. Reposting would likely draw the same reaction. | J100: Nobody in the group cares about local issues. | K100: More likely it's the wrong place. Such groups tend to stick to practical, local topics. | L100: Approved | M100: Bulk-approved by founder; item review pending | P100: =MAX(LEN(G100),LEN(I100),LEN(K100)) | Q100: These norms are genuinely, if informally, enforced, and posts outside the expected range can draw a noticeably cool or corrective response from the group. | R100: Observe the general tone and typical topics of a local community group for a while before posting anything opinionated, and keep contributions practical and local (recommendations, lost items, local news).
...
